tma_functions/__init__.py
tma_functions/auth.py
tma_functions-0.1.2.dist-info/METADATA
tma_functions-0.1.2.dist-info/WHEEL
tma_functions-0.1.2.dist-info/licenses/LICENSE
tma_functions-0.1.2.dist-info/RECORD
