Metadata-Version: 2.4
Name: tma-functions
Version: 0.1.2
Summary: Helper functions for Telegram Mini Apps.
Project-URL: Homepage, https://github.com/romankurnovskii/tma-functions
Project-URL: Documentation, https://github.com/romankurnovskii/tma-functions#readme
Project-URL: Repository, https://github.com/romankurnovskii/tma-functions.git
Project-URL: Issues, https://github.com/romankurnovskii/tma-functions/issues
Author: Roman Kurnovskii
License-Expression: MIT
License-File: LICENSE
Classifier: Development Status :: 4 - Beta
Classifier: License :: OSI Approved :: MIT License
Classifier: Operating System :: OS Independent
Classifier: Programming Language :: Python :: 3
Classifier: Programming Language :: Python :: 3.9
Classifier: Programming Language :: Python :: 3.10
Classifier: Programming Language :: Python :: 3.11
Classifier: Programming Language :: Python :: 3.12
Requires-Python: >=3.9
Requires-Dist: pydantic
Provides-Extra: dev
Requires-Dist: hatch>=1.14.1; extra == 'dev'
Requires-Dist: mypy>=1.16.0; extra == 'dev'
Requires-Dist: pytest-cov>=6.1.1; extra == 'dev'
Requires-Dist: pytest>=8.4.0; extra == 'dev'
Requires-Dist: ruff>=0.11.13; extra == 'dev'
